swarmauri_storage_github_release/__init__.py
swarmauri_storage_github_release/gh_release_storage_adapter.py
swarmauri_storage_github_release-0.3.0.dev4.dist-info/LICENSE
swarmauri_storage_github_release-0.3.0.dev4.dist-info/METADATA
swarmauri_storage_github_release-0.3.0.dev4.dist-info/WHEEL
swarmauri_storage_github_release-0.3.0.dev4.dist-info/entry_points.txt
swarmauri_storage_github_release-0.3.0.dev4.dist-info/RECORD
